auto_launch/__init__.py
auto_launch/cli.py
auto_launch/kill.py
auto_launch/run.py
auto_launch/lib/__init__.py
auto_launch/lib/cluster_manager.py
auto_launch/lib/host_discovery.py
auto_launch/lib/node_executor.py
auto_launch/scripts/fix_ssh_keys.sh
auto_launch/scripts/init_cluster.py
auto_launch/scripts/run.sh
auto_launch/scripts/test_ssh.sh
auto_launch/scripts/verify_ssh_keys.sh
auto_launch/scripts/wait.sh
auto_launch/scripts/wait_for_debug.sh
dist_launch/__init__.py
dist_launch/cli.py
dist_launch/kill.py
dist_launch/nccl_tests.py
dist_launch/run.py
dist_launch/lib/__init__.py
dist_launch/lib/cluster_manager.py
dist_launch/lib/host_discovery.py
dist_launch/lib/node_executor.py
dist_launch/scripts/fix_ssh_keys.sh
dist_launch/scripts/init_cluster.py
dist_launch/scripts/nccl_tests.sh
dist_launch/scripts/run.sh
dist_launch/scripts/test_ssh.sh
dist_launch/scripts/verify_ssh_keys.sh
dist_launch/scripts/wait.sh
dist_launch/ssh-key/id_rsa
dist_launch/ssh-key/id_rsa.pub
dist_launch-0.1.11.dist-info/METADATA
dist_launch-0.1.11.dist-info/WHEEL
dist_launch-0.1.11.dist-info/entry_points.txt
dist_launch-0.1.11.dist-info/top_level.txt
dist_launch-0.1.11.dist-info/RECORD
